Metadata-Version: 2.1
Name: msookies
Version: 1.0.3
Summary: Loads decrypted cookiejars from Chromium based browsers running on Windows.
Home-page: https://github.com/yportne8/mscookies/
Author: CS Kim
Author-email: yportne8@gmail.com
License: MIT
Classifier: License :: OSI Approved :: MIT License
Classifier: Programming Language :: Python
Classifier: Programming Language :: Python :: 3
Classifier: Programming Language :: Python :: 3.6
Classifier: Programming Language :: Python :: Implementation :: CPython
Requires-Python: >=3.6.0
License-File: LICENSE
